LICENSE.txt
MANIFEST.in
README.rst
pyproject.toml
setup.py
tests/test_utils.py
tutor_discovery.egg-info/PKG-INFO
tutor_discovery.egg-info/SOURCES.txt
tutor_discovery.egg-info/dependency_links.txt
tutor_discovery.egg-info/entry_points.txt
tutor_discovery.egg-info/requires.txt
tutor_discovery.egg-info/top_level.txt
tutordiscovery/__about__.py
tutordiscovery/__init__.py
tutordiscovery/plugin.py
tutordiscovery/utils.py
tutordiscovery/patches/caddyfile
tutordiscovery/patches/dev-docker-compose-jobs-services
tutordiscovery/patches/discovery-common-settings
tutordiscovery/patches/k8s-deployments
tutordiscovery/patches/k8s-jobs
tutordiscovery/patches/k8s-services
tutordiscovery/patches/k8s-volumes
tutordiscovery/patches/kustomization-configmapgenerator
tutordiscovery/patches/local-docker-compose-caddy-aliases
tutordiscovery/patches/local-docker-compose-dev-services
tutordiscovery/patches/local-docker-compose-jobs-services
tutordiscovery/patches/local-docker-compose-permissions-command
tutordiscovery/patches/local-docker-compose-permissions-volumes
tutordiscovery/patches/local-docker-compose-services
tutordiscovery/patches/openedx-lms-common-settings
tutordiscovery/templates/discovery/apps/settings/partials/common.py
tutordiscovery/templates/discovery/apps/settings/tutor/__init__.py
tutordiscovery/templates/discovery/apps/settings/tutor/development.py
tutordiscovery/templates/discovery/apps/settings/tutor/production.py
tutordiscovery/templates/discovery/build/discovery/Dockerfile
tutordiscovery/templates/discovery/build/discovery/assets.py
tutordiscovery/templates/discovery/tasks/discovery/init
tutordiscovery/templates/discovery/tasks/lms/init
tutordiscovery/templates/discovery/tasks/mysql/init